{
  "url": "https://careers-westernsouthern.icims.com/jobs/23639/job?mobile=true&needsRedirect=false",
  "data": {
    "success": true,
    "platform": "icims",
    "description": "<h2>Overview</h2> <p>Provide data and reporting support for multiple business customers. Work includes migrating reports from outdated technology to Tableau and Cognos. You'll demonstrate strong analytical problem-solving skills to assure accuracy. You will build strong relationships as you communicate successfully with associates at all levels to obtain their approval on the newly converted reports. You'll also work to develop new reports and visualizations through iterative development cycles with business customers.</p> <h2>Responsibilities</h2> <p><strong>What you will do:</strong></p> <ul> <li>Crystal Reports: Assist conversion of outdated reports to Tableau/Cognos.</li> <li>Tableau: Develop dynamic and interactive data visualizations.</li> <li>Cognos: Create reports intended for distributed output.</li> <li>TFS: Use Team Foundation Server to log and track data work.</li> <li>Performs other duties as assigned.</li> <li>Complies with all policies and standards.</li> </ul> <h2>Qualifications</h2> <ul> <li>Incoming junior/senior or current graduate student. - Required</li> <li>Major field of study in Data, Analytics or a related field. - Required</li> <li>Strong working knowledge of SQL in a server-based environment, using tools such as PL/SQL Developer, Oracle Developer, or MS SQL Server Management Studio</li> <li>Demonstrated knowledge of relational databases</li> <li>Beginner to moderate experience with business intelligence tools like Tableau, Cognos, Microsoft BI, etc.</li> <li>Demonstrated ability to respond in a positive, professional manner to multiple deadlines and shifting priorities</li> <li>Demonstrated experience identifying and solving problems independently.</li> </ul> <p><strong>Work Setting/Position Demands:</strong></p> <ul> <li>Works in an office setting and remains in a stationary position for long periods of time while working at a desk, on a computer or with other standard office equipment, or while in meetings.</li> <li>Requires the ability to verbally communicate and exchange accurate information to customers and associates on a regular basis.</li> <li>Requires visual acuity to read and interpret a variety of correspondence, procedures, reports and forms via paper and electronic documents, visual inspection involving small defects; small parts, and/or operation of machinery (including inspection); using measurement devices continuously. Visual acuity is required to determine accuracy, neatness, and thoroughness of work assigned.</li> <li>Requires the ability to prepare written correspondence, reports and forms using prescribed formats and conforming to rules of punctuation, grammar, diction, and style on a regular basis.</li> <li>Requires the ability to apply principles of logical thinking to define problems, collect data, establish facts, and draw valid conclusions</li> <li>Performs substantial movement of wrists, hands, and fingers for continuous computer work.</li> <li>Extended hours required during peak workloads or special projects/events.</li> </ul> <p><strong>Travel Requirements:</strong></p> <ul> <li>None</li> </ul>",
    "requirements": null,
    "responsibilities": null,
    "metadata": {
      "source": "generic",
      "extractionMethod": "json-ld",
      "url": "https://careers-westernsouthern.icims.com/jobs/23639/job?mobile=true&needsRedirect=false",
      "fetchedAt": "2025-12-14T21:31:38.618Z"
    }
  },
  "cachedAt": 1765747898618
}