{
  "url": "https://ats.rippling.com/veryable-careers/jobs/12a23532-21a0-4ba5-afc7-24c9767ab64c",
  "data": {
    "success": true,
    "platform": "generic",
    "description": "Mobile Engineer Internship (iOS/Android) Location: Dallas, TX (On-Site) Remote candidates will not be considered. We are located in the wes...",
    "requirements": null,
    "responsibilities": null,
    "metadata": {
      "source": "generic",
      "extractionMethod": "meta-tags",
      "url": "https://ats.rippling.com/veryable-careers/jobs/12a23532-21a0-4ba5-afc7-24c9767ab64c",
      "fetchedAt": "2025-12-04T22:06:50.689Z"
    }
  },
  "cachedAt": 1764886010690
}